aioscheduler/__init__.py
aioscheduler/manager.py
aioscheduler/scheduler.py
aioscheduler/task.py
aioscheduler-1.4.2.dist-info/LICENSE
aioscheduler-1.4.2.dist-info/METADATA
aioscheduler-1.4.2.dist-info/WHEEL
aioscheduler-1.4.2.dist-info/top_level.txt
aioscheduler-1.4.2.dist-info/RECORD
