Metadata-Version: 2.1
Name: aioscheduler
Version: 1.4.2
Summary: Scalable, high-performance AsyncIO task scheduler
Home-page: https://github.com/Gelbpunkt/aioscheduler
Author: Jens Reidel
Author-email: adrian@travitia.xyz
License: UNKNOWN
Platform: UNKNOWN
Classifier: Programming Language :: Python :: 3.7
Classifier: Programming Language :: Python :: 3.8
Classifier: Programming Language :: Python :: 3.9
Classifier: License :: OSI Approved :: MIT License
Classifier: Intended Audience :: Developers
Classifier: Topic :: Software Development :: Libraries
Classifier: Topic :: Software Development :: Libraries :: Python Modules
Classifier: Operating System :: OS Independent
Requires-Python: >=3.7
